pyrtdb/__init__.py
pyrtdb/__version__.py
pyrtdb/callso.py
pyrtdb/connection.py
pyrtdb/constant.py
pyrtdb/converter.py
pyrtdb/cursor.py
pyrtdb/datastructure.py
pyrtdb/exception.py
pyrtdb/log.py
pyrtdb/time.py
pyrtdb/dll/linux/libtsdb.so
pyrtdb/dll/windows/win32/tsdb.dll
pyrtdb/dll/windows/x64/tsdb.dll
pyrtdb-0.0.1.dev4.data/data/pyrtdb/dll/linux/libtsdb.so
pyrtdb-0.0.1.dev4.data/data/pyrtdb/dll/windows/tsdb.dll
tests/__init__.py
tests/test_callso.py
tests/test_connection.py
tests/test_cursor.py
tests/test_time.py
pyrtdb-0.0.1.dev4.dist-info/LICENSE
pyrtdb-0.0.1.dev4.dist-info/METADATA
pyrtdb-0.0.1.dev4.dist-info/WHEEL
pyrtdb-0.0.1.dev4.dist-info/top_level.txt
pyrtdb-0.0.1.dev4.dist-info/RECORD
