Metadata-Version: 2.1
Name: pyrtdb
Version: 0.0.1.dev4
Summary: Python connector for rtdb
Home-page: 
Author: Patrick
Author-email: pengzhao@rtdb.com
License: GNU Lesser General Public License v3 (LGPLv3)
Platform: UNKNOWN
Classifier: Programming Language :: Python :: 3
Classifier: License :: OSI Approved :: GNU Lesser General Public License v3 (LGPLv3)
Classifier: Operating System :: OS Independent
Requires-Python: >=3.6
License-File: LICENSE
